black_configparser/__init__.py
black_configparser/black_configparser.py
black_configparser/py.typed
black_configparser-0.2.0b2.dist-info/LICENSE
black_configparser-0.2.0b2.dist-info/METADATA
black_configparser-0.2.0b2.dist-info/WHEEL
black_configparser-0.2.0b2.dist-info/entry_points.txt
black_configparser-0.2.0b2.dist-info/top_level.txt
black_configparser-0.2.0b2.dist-info/RECORD
