Metadata-Version: 2.1
Name: black-configparser
Version: 0.2.0b2
Summary: Seamless Proxy CLI for black ("The uncompromising code formatter") with support for non-pyproject.toml config files
Home-page: https://github.com/danie1k/python-black-configparser
Author: Daniel Kuruc
Author-email: daniel@kuruc.dev
License: MIT
Project-URL: Code, https://github.com/danie1k/python-black-configparser
Project-URL: Issue tracker, https://github.com/danie1k/python-black-configparser/issues
Keywords: automation formatter yapf autopep8 pyfmt gofmt rustfmt black white brunette
Platform: UNKNOWN
Classifier: Development Status :: 4 - Beta
Classifier: Environment :: Console
Classifier: Intended Audience :: Developers
Classifier: License :: OSI Approved :: MIT License
Classifier: Operating System :: OS Independent
Classifier: Programming Language :: Python
Classifier: Programming Language :: Python :: 3 :: Only
Classifier: Programming Language :: Python :: 3.6
Classifier: Programming Language :: Python :: 3.7
Classifier: Programming Language :: Python :: 3.8
Classifier: Programming Language :: Python :: 3.9
Classifier: Topic :: Software Development :: Libraries :: Python Modules
Classifier: Topic :: Software Development :: Quality Assurance
Requires-Python: >=3.6
Requires-Dist: black (>=18.6b2)
Provides-Extra: lint
Requires-Dist: black (>=18.6b2) ; extra == 'lint'
Requires-Dist: flake8 (>=3.8.0) ; extra == 'lint'
Requires-Dist: isort (>=5.6.0) ; extra == 'lint'
Requires-Dist: mypy (>=0.790) ; extra == 'lint'
Requires-Dist: pylint (>=2.6.0) ; extra == 'lint'
Provides-Extra: tests
Requires-Dist: coverage (>=5.0) ; extra == 'tests'
Requires-Dist: pytest (>=6.0) ; extra == 'tests'
Requires-Dist: pytest-sugar (>=0.9) ; extra == 'tests'
